ndict_tools/__init__.py
ndict_tools/core.py
ndict_tools/exception.py
ndict_tools/tools.py
ndict_tools-0.9.0.dist-info/METADATA
ndict_tools-0.9.0.dist-info/WHEEL
ndict_tools-0.9.0.dist-info/licenses/LICENSE.md
ndict_tools-0.9.0.dist-info/RECORD
