Metadata-Version: 2.4
Name: ndict-tools
Version: 0.9.0
Summary: An implementation of nested dictionaries
Project-URL: Homepage, https://github.com/biface/ndt
Project-URL: Documentation, https://ndict-tools.readthedocs.io/en/latest/
Project-URL: Repository, https://github.com/biface/ndt.git
Project-URL: Issues, https://github.com/biface/ndt/issues
Author: biface
License-File: LICENSE.md
Classifier: Development Status :: 4 - Beta
Classifier: Intended Audience :: Developers
Classifier: License :: CeCILL-C Free Software License Agreement (CECILL-C)
Classifier: Operating System :: OS Independent
Classifier: Programming Language :: Python :: 3
Classifier: Programming Language :: Python :: 3.9
Classifier: Programming Language :: Python :: 3.10
Classifier: Programming Language :: Python :: 3.11
Classifier: Programming Language :: Python :: 3.12
Classifier: Topic :: Utilities
Requires-Python: >=3.9
